<?xml version="1.0" encoding="UTF-8"?>
<tour start="node6" appversion="7.1.2" apprev="20913" hassounds="0">
  <panorama id="node6" hideabout="1">
    <input width="2000" levelbiashidpi="1.000" levelbias="0.400" leveltileurl="tiles/node6/cf_%c/l_%l/c_%x/tile_%y.jpg" overlap="1" height="2000" levelingroll="0" leveltilesize="510" levelingpitch="0">
      <level height="2000" width="2000" preload="0" predecode="0"/>
      <level height="1000" width="1000" preload="0" predecode="0"/>
      <level height="500" width="500" preload="1" predecode="1"/>
      <preview color="0x808080" strip="1"/>
    </input>
    <view pannorth="0" fovmode="2">
      <start tilt="-7.25424" pan="-3.94854" fov="127.548" projection="4"/>
      <flyin tilt="-90" pan="0" fov="170" projection="9"/>
      <min tilt="-90" pan="0" fovpixel="2"/>
      <max fovstereographic="330" tilt="90" scaletofit="1" pan="360" fov="140" fovfisheye="360"/>
    </view>
    <userdata tags="202411155052701" longitude="129.140719" customnodeid="" comment="" copyright="" author="" datetime="2024:11:20 09:19:15" altitude="107.32" latitude="35.806231" info="" heading="0" description="" nodeid="node6" source="" title="세대현관"/>
    <hotspots height="20" width="180" wordwrap="1" smoothmovement="0">
      <label background="1" borderradius="1" width="180" borderalpha="1" border="1" textcolor="0x000000" backgroundalpha="1" enabled="1" height="20" backgroundcolor="0xffffff" wordwrap="1" bordercolor="0x000000" textalpha="1"/>
      <polystyle backgroundcolor="0x0000ff" borderalpha="1" mode="0" bordercolor="0x0000ff" backgroundalpha="0.25098" handcursor="1"/>
      <hotspot target="" skinid="ht_node" tilt="-6.56" pan="0.14" id="Point01" url="{node5}" description="" title="현관"/>
    </hotspots>
    <media/>
    <transition zoomin="0" delay="none" type="crossdissolve" zoomspeed="2" zoomafteroutfov="40" enabled="1" softedge="0" zoomfov="40" zoomafterinfov="140" blendcolor="0x000000" zoomout="0" blendtime="1" zoomoutpause="1"/>
    <autorotate nodefilter="" returntohorizon="0.000" noderandom="1" delay="10.00" nodedelay="0.00" horizonfromdefview="0" enabled="1" speed="0.020" useanimation="0" startloaded="0"/>
    <animation syncanimationwithvideo="0" useinautorotation="0" animsequence="Animation01" clipsrandom="0"/>
    <control lockedkeyboardzoom="0" invertcontrol="1" rubberband="0" contextprojections="0" lockedmouse="0" dblclickfullscreen="0" lockedwheel="0" speedwheel="1" lockedkeyboard="0" invertwheel="0" sensitivity="8" contextfullscreen="1" simulatemass="1" hideabout="1" zoomcentercursor="1" contextvr="1"/>
  </panorama>
  <panorama id="node5" hideabout="1">
    <input width="2000" levelbiashidpi="1.000" levelbias="0.400" leveltileurl="tiles/node5/cf_%c/l_%l/c_%x/tile_%y.jpg" overlap="1" height="2000" levelingroll="0" leveltilesize="510" levelingpitch="0">
      <level height="2000" width="2000" preload="0" predecode="0"/>
      <level height="1000" width="1000" preload="0" predecode="0"/>
      <level height="500" width="500" preload="1" predecode="1"/>
      <preview color="0x808080" strip="1"/>
    </input>
    <view pannorth="0" fovmode="2">
      <start tilt="-11.0388" pan="-174.369" fov="129.808" projection="4"/>
      <flyin tilt="-90" pan="0" fov="170" projection="9"/>
      <min tilt="-90" pan="0" fovpixel="2"/>
      <max fovstereographic="330" tilt="90" scaletofit="1" pan="360" fov="140" fovfisheye="360"/>
    </view>
    <userdata tags="202411155052701" longitude="129.140719" customnodeid="" comment="" copyright="" author="" datetime="2024:11:20 09:19:10" altitude="107.32" latitude="35.806231" info="" heading="0" description="" nodeid="node5" source="" title="현관"/>
    <hotspots height="20" width="180" wordwrap="1" smoothmovement="0">
      <label background="1" borderradius="1" width="180" borderalpha="1" border="1" textcolor="0x000000" backgroundalpha="1" enabled="1" height="20" backgroundcolor="0xffffff" wordwrap="1" bordercolor="0x000000" textalpha="1"/>
      <polystyle backgroundcolor="0x0000ff" borderalpha="1" mode="0" bordercolor="0x0000ff" backgroundalpha="0.25098" handcursor="1"/>
      <hotspot target="" skinid="ht_node" tilt="-14.31" pan="-0.56" id="Point01" url="{node6}" description="" title="세대현관"/>
      <hotspot target="" skinid="ht_node" tilt="-20.77" pan="-104.74" id="Point02" url="{node4}" description="" title="현관창고"/>
      <hotspot target="" skinid="ht_node" tilt="-35.79" pan="-167.8" id="Point03" url="{node14}" description="" title="복도1"/>
    </hotspots>
    <media/>
    <transition zoomin="0" delay="none" type="crossdissolve" zoomspeed="2" zoomafteroutfov="40" enabled="1" softedge="0" zoomfov="40" zoomafterinfov="140" blendcolor="0x000000" zoomout="0" blendtime="1" zoomoutpause="1"/>
    <autorotate nodefilter="" returntohorizon="0.000" noderandom="1" delay="10.00" nodedelay="0.00" horizonfromdefview="0" enabled="1" speed="0.020" useanimation="0" startloaded="0"/>
    <animation syncanimationwithvideo="0" useinautorotation="0" animsequence="Animation01" clipsrandom="0"/>
    <control lockedkeyboardzoom="0" invertcontrol="1" rubberband="0" contextprojections="0" lockedmouse="0" dblclickfullscreen="0" lockedwheel="0" speedwheel="1" lockedkeyboard="0" invertwheel="0" sensitivity="8" contextfullscreen="1" simulatemass="1" hideabout="1" zoomcentercursor="1" contextvr="1"/>
  </panorama>
  <panorama id="node4" hideabout="1">
    <input width="2000" levelbiashidpi="1.000" levelbias="0.400" leveltileurl="tiles/node4/cf_%c/l_%l/c_%x/tile_%y.jpg" overlap="1" height="2000" levelingroll="0" leveltilesize="510" levelingpitch="0">
      <level height="2000" width="2000" preload="0" predecode="0"/>
      <level height="1000" width="1000" preload="0" predecode="0"/>
      <level height="500" width="500" preload="1" predecode="1"/>
      <preview color="0x808080" strip="1"/>
    </input>
    <view pannorth="0" fovmode="2">
      <start tilt="-29.1333" pan="-63.8674" fov="140.418" projection="4"/>
      <flyin tilt="-90" pan="0" fov="170" projection="9"/>
      <min tilt="-90" pan="0" fovpixel="2"/>
      <max fovstereographic="330" tilt="90" scaletofit="1" pan="360" fov="140" fovfisheye="360"/>
    </view>
    <userdata tags="202411155052701" longitude="129.140719" customnodeid="" comment="" copyright="" author="" datetime="2024:11:20 09:19:05" altitude="107.32" latitude="35.806231" info="" heading="0" description="" nodeid="node4" source="" title="현관창고"/>
    <hotspots height="20" width="180" wordwrap="1" smoothmovement="0">
      <label background="1" borderradius="1" width="180" borderalpha="1" border="1" textcolor="0x000000" backgroundalpha="1" enabled="1" height="20" backgroundcolor="0xffffff" wordwrap="1" bordercolor="0x000000" textalpha="1"/>
      <polystyle backgroundcolor="0x0000ff" borderalpha="1" mode="0" bordercolor="0x0000ff" backgroundalpha="0.25098" handcursor="1"/>
      <hotspot target="" skinid="ht_node" tilt="-48.5" pan="-180.33" id="Point01" url="{node5}" description="" title="현관"/>
    </hotspots>
    <media/>
    <transition zoomin="0" delay="none" type="crossdissolve" zoomspeed="2" zoomafteroutfov="40" enabled="1" softedge="0" zoomfov="40" zoomafterinfov="140" blendcolor="0x000000" zoomout="0" blendtime="1" zoomoutpause="1"/>
    <autorotate nodefilter="" returntohorizon="0.000" noderandom="1" delay="10.00" nodedelay="0.00" horizonfromdefview="0" enabled="1" speed="0.020" useanimation="0" startloaded="0"/>
    <animation syncanimationwithvideo="0" useinautorotation="0" animsequence="Animation01" clipsrandom="0"/>
    <control lockedkeyboardzoom="0" invertcontrol="1" rubberband="0" contextprojections="0" lockedmouse="0" dblclickfullscreen="0" lockedwheel="0" speedwheel="1" lockedkeyboard="0" invertwheel="0" sensitivity="8" contextfullscreen="1" simulatemass="1" hideabout="1" zoomcentercursor="1" contextvr="1"/>
  </panorama>
  <panorama id="node14" hideabout="1">
    <input width="2000" levelbiashidpi="1.000" levelbias="0.400" leveltileurl="tiles/node14/cf_%c/l_%l/c_%x/tile_%y.jpg" overlap="1" height="2000" levelingroll="0" leveltilesize="510" levelingpitch="0">
      <level height="2000" width="2000" preload="0" predecode="0"/>
      <level height="1000" width="1000" preload="0" predecode="0"/>
      <level height="500" width="500" preload="1" predecode="1"/>
      <preview color="0x808080" strip="1"/>
    </input>
    <view pannorth="0" fovmode="2">
      <start tilt="-11.1182" pan="-179.376" fov="140.418" projection="4"/>
      <flyin tilt="-90" pan="0" fov="170" projection="9"/>
      <min tilt="-90" pan="0" fovpixel="2"/>
      <max fovstereographic="330" tilt="90" scaletofit="1" pan="360" fov="140" fovfisheye="360"/>
    </view>
    <userdata tags="202411155052701" longitude="129.140719" customnodeid="" comment="" copyright="" author="" datetime="2024:11:20 09:18:18" altitude="107.32" latitude="35.806231" info="" heading="0" description="" nodeid="node14" source="" title="복도1"/>
    <hotspots height="20" width="180" wordwrap="1" smoothmovement="0">
      <label background="1" borderradius="1" width="180" borderalpha="1" border="1" textcolor="0x000000" backgroundalpha="1" enabled="1" height="20" backgroundcolor="0xffffff" wordwrap="1" bordercolor="0x000000" textalpha="1"/>
      <polystyle backgroundcolor="0x0000ff" borderalpha="1" mode="0" bordercolor="0x0000ff" backgroundalpha="0.25098" handcursor="1"/>
      <hotspot target="" skinid="ht_node" tilt="-32.99" pan="-355.81" id="Point01" url="{node3}" description="" title="욕실1"/>
      <hotspot target="" skinid="ht_node" tilt="-40.34" pan="-58.12" id="Point02" url="{node5}" description="" title="현관"/>
      <hotspot target="" skinid="ht_node" tilt="-40.21" pan="-318.91" id="Point03" url="{node2}" description="" title="침실2"/>
      <hotspot target="" skinid="ht_node" tilt="-19.1" pan="-174.23" id="Point04" url="{node10}" description="" title="복도2"/>
      <hotspot target="" skinid="ht_node" tilt="-28.02" pan="-200.46" id="Point05" url="{node1}" description="" title="침실3"/>
    </hotspots>
    <media/>
    <transition zoomin="0" delay="none" type="crossdissolve" zoomspeed="2" zoomafteroutfov="40" enabled="1" softedge="0" zoomfov="40" zoomafterinfov="140" blendcolor="0x000000" zoomout="0" blendtime="1" zoomoutpause="1"/>
    <autorotate nodefilter="" returntohorizon="0.000" noderandom="1" delay="10.00" nodedelay="0.00" horizonfromdefview="0" enabled="1" speed="0.020" useanimation="0" startloaded="0"/>
    <animation syncanimationwithvideo="0" useinautorotation="0" animsequence="Animation01" clipsrandom="0"/>
    <control lockedkeyboardzoom="0" invertcontrol="1" rubberband="0" contextprojections="0" lockedmouse="0" dblclickfullscreen="0" lockedwheel="0" speedwheel="1" lockedkeyboard="0" invertwheel="0" sensitivity="8" contextfullscreen="1" simulatemass="1" hideabout="1" zoomcentercursor="1" contextvr="1"/>
  </panorama>
  <panorama id="node3" hideabout="1">
    <input width="2000" levelbiashidpi="1.000" levelbias="0.400" leveltileurl="tiles/node3/cf_%c/l_%l/c_%x/tile_%y.jpg" overlap="1" height="2000" levelingroll="0" leveltilesize="510" levelingpitch="0">
      <level height="2000" width="2000" preload="0" predecode="0"/>
      <level height="1000" width="1000" preload="0" predecode="0"/>
      <level height="500" width="500" preload="1" predecode="1"/>
      <preview color="0x808080" strip="1"/>
    </input>
    <view pannorth="0" fovmode="2">
      <start tilt="-27.2866" pan="-44.191" fov="140.418" projection="4"/>
      <flyin tilt="-90" pan="0" fov="170" projection="9"/>
      <min tilt="-90" pan="0" fovpixel="2"/>
      <max fovstereographic="330" tilt="90" scaletofit="1" pan="360" fov="140" fovfisheye="360"/>
    </view>
    <userdata tags="202411155052701" longitude="129.140719" customnodeid="" comment="" copyright="" author="" datetime="2024:11:20 09:19:00" altitude="107.32" latitude="35.806231" info="" heading="0" description="" nodeid="node3" source="" title="욕실1"/>
    <hotspots height="20" width="180" wordwrap="1" smoothmovement="0">
      <label background="1" borderradius="1" width="180" borderalpha="1" border="1" textcolor="0x000000" backgroundalpha="1" enabled="1" height="20" backgroundcolor="0xffffff" wordwrap="1" bordercolor="0x000000" textalpha="1"/>
      <polystyle backgroundcolor="0x0000ff" borderalpha="1" mode="0" bordercolor="0x0000ff" backgroundalpha="0.25098" handcursor="1"/>
      <hotspot target="" skinid="ht_node" tilt="-39.67" pan="-220.46" id="Point01" url="{node14}" description="" title="복도1"/>
    </hotspots>
    <media/>
    <transition zoomin="0" delay="none" type="crossdissolve" zoomspeed="2" zoomafteroutfov="40" enabled="1" softedge="0" zoomfov="40" zoomafterinfov="140" blendcolor="0x000000" zoomout="0" blendtime="1" zoomoutpause="1"/>
    <autorotate nodefilter="" returntohorizon="0.000" noderandom="1" delay="10.00" nodedelay="0.00" horizonfromdefview="0" enabled="1" speed="0.020" useanimation="0" startloaded="0"/>
    <animation syncanimationwithvideo="0" useinautorotation="0" animsequence="Animation01" clipsrandom="0"/>
    <control lockedkeyboardzoom="0" invertcontrol="1" rubberband="0" contextprojections="0" lockedmouse="0" dblclickfullscreen="0" lockedwheel="0" speedwheel="1" lockedkeyboard="0" invertwheel="0" sensitivity="8" contextfullscreen="1" simulatemass="1" hideabout="1" zoomcentercursor="1" contextvr="1"/>
  </panorama>
  <panorama id="node2" hideabout="1">
    <input width="2000" levelbiashidpi="1.000" levelbias="0.400" leveltileurl="tiles/node2/cf_%c/l_%l/c_%x/tile_%y.jpg" overlap="1" height="2000" levelingroll="0" leveltilesize="510" levelingpitch="0">
      <level height="2000" width="2000" preload="0" predecode="0"/>
      <level height="1000" width="1000" preload="0" predecode="0"/>
      <level height="500" width="500" preload="1" predecode="1"/>
      <preview color="0x808080" strip="1"/>
    </input>
    <view pannorth="0" fovmode="2">
      <start tilt="-21.7201" pan="-178.745" fov="149.25" projection="4"/>
      <flyin tilt="-90" pan="0" fov="170" projection="9"/>
      <min tilt="-90" pan="0" fovpixel="2"/>
      <max fovstereographic="330" tilt="90" scaletofit="1" pan="360" fov="140" fovfisheye="360"/>
    </view>
    <userdata tags="202411155052701" longitude="129.140719" customnodeid="" comment="" copyright="" author="" datetime="2024:11:20 09:18:56" altitude="107.32" latitude="35.806231" info="" heading="0" description="" nodeid="node2" source="" title="침실2"/>
    <hotspots height="20" width="180" wordwrap="1" smoothmovement="0">
      <label background="1" borderradius="1" width="180" borderalpha="1" border="1" textcolor="0x000000" backgroundalpha="1" enabled="1" height="20" backgroundcolor="0xffffff" wordwrap="1" bordercolor="0x000000" textalpha="1"/>
      <polystyle backgroundcolor="0x0000ff" borderalpha="1" mode="0" bordercolor="0x0000ff" backgroundalpha="0.25098" handcursor="1"/>
      <hotspot target="" skinid="ht_node" tilt="-24.16" pan="-206.36" id="Point01" url="{node14}" description="" title="복도1"/>
    </hotspots>
    <media/>
    <transition zoomin="0" delay="none" type="crossdissolve" zoomspeed="2" zoomafteroutfov="40" enabled="1" softedge="0" zoomfov="40" zoomafterinfov="140" blendcolor="0x000000" zoomout="0" blendtime="1" zoomoutpause="1"/>
    <autorotate nodefilter="" returntohorizon="0.000" noderandom="1" delay="10.00" nodedelay="0.00" horizonfromdefview="0" enabled="1" speed="0.020" useanimation="0" startloaded="0"/>
    <animation syncanimationwithvideo="0" useinautorotation="0" animsequence="Animation01" clipsrandom="0"/>
    <control lockedkeyboardzoom="0" invertcontrol="1" rubberband="0" contextprojections="0" lockedmouse="0" dblclickfullscreen="0" lockedwheel="0" speedwheel="1" lockedkeyboard="0" invertwheel="0" sensitivity="8" contextfullscreen="1" simulatemass="1" hideabout="1" zoomcentercursor="1" contextvr="1"/>
  </panorama>
  <panorama id="node1" hideabout="1">
    <input width="2000" levelbiashidpi="1.000" levelbias="0.400" leveltileurl="tiles/node1/cf_%c/l_%l/c_%x/tile_%y.jpg" overlap="1" height="2000" levelingroll="0" leveltilesize="510" levelingpitch="0">
      <level height="2000" width="2000" preload="0" predecode="0"/>
      <level height="1000" width="1000" preload="0" predecode="0"/>
      <level height="500" width="500" preload="1" predecode="1"/>
      <preview color="0x808080" strip="1"/>
    </input>
    <view pannorth="0" fovmode="2">
      <start tilt="-18.6956" pan="176.274" fov="137.973" projection="4"/>
      <flyin tilt="-90" pan="0" fov="170" projection="9"/>
      <min tilt="-90" pan="0" fovpixel="2"/>
      <max fovstereographic="330" tilt="90" scaletofit="1" pan="360" fov="140" fovfisheye="360"/>
    </view>
    <userdata tags="202411155052701" longitude="129.140719" customnodeid="" comment="" copyright="" author="" datetime="2024:11:20 09:18:51" altitude="107.32" latitude="35.806231" info="" heading="0" description="" nodeid="node1" source="" title="침실3"/>
    <hotspots height="20" width="180" wordwrap="1" smoothmovement="0">
      <label background="1" borderradius="1" width="180" borderalpha="1" border="1" textcolor="0x000000" backgroundalpha="1" enabled="1" height="20" backgroundcolor="0xffffff" wordwrap="1" bordercolor="0x000000" textalpha="1"/>
      <polystyle backgroundcolor="0x0000ff" borderalpha="1" mode="0" bordercolor="0x0000ff" backgroundalpha="0.25098" handcursor="1"/>
      <hotspot target="" skinid="ht_node" tilt="-20.87" pan="-200.22" id="Point01" url="{node14}" description="" title="복도1"/>
    </hotspots>
    <media/>
    <transition zoomin="0" delay="none" type="crossdissolve" zoomspeed="2" zoomafteroutfov="40" enabled="1" softedge="0" zoomfov="40" zoomafterinfov="140" blendcolor="0x000000" zoomout="0" blendtime="1" zoomoutpause="1"/>
    <autorotate nodefilter="" returntohorizon="0.000" noderandom="1" delay="10.00" nodedelay="0.00" horizonfromdefview="0" enabled="1" speed="0.020" useanimation="0" startloaded="0"/>
    <animation syncanimationwithvideo="0" useinautorotation="0" animsequence="Animation01" clipsrandom="0"/>
    <control lockedkeyboardzoom="0" invertcontrol="1" rubberband="0" contextprojections="0" lockedmouse="0" dblclickfullscreen="0" lockedwheel="0" speedwheel="1" lockedkeyboard="0" invertwheel="0" sensitivity="8" contextfullscreen="1" simulatemass="1" hideabout="1" zoomcentercursor="1" contextvr="1"/>
  </panorama>
  <panorama id="node10" hideabout="1">
    <input width="2000" levelbiashidpi="1.000" levelbias="0.400" leveltileurl="tiles/node10/cf_%c/l_%l/c_%x/tile_%y.jpg" overlap="1" height="2000" levelingroll="0" leveltilesize="510" levelingpitch="0">
      <level height="2000" width="2000" preload="0" predecode="0"/>
      <level height="1000" width="1000" preload="0" predecode="0"/>
      <level height="500" width="500" preload="1" predecode="1"/>
      <preview color="0x808080" strip="1"/>
    </input>
    <view pannorth="0" fovmode="2">
      <start tilt="-5.06472" pan="135.12" fov="137.973" projection="4"/>
      <flyin tilt="-90" pan="0" fov="170" projection="9"/>
      <min tilt="-90" pan="0" fovpixel="2"/>
      <max fovstereographic="330" tilt="90" scaletofit="1" pan="360" fov="140" fovfisheye="360"/>
    </view>
    <userdata tags="202411155052701" longitude="129.140719" customnodeid="" comment="" copyright="" author="" datetime="2024:11:20 09:17:59" altitude="107.32" latitude="35.806231" info="" heading="0" description="" nodeid="node10" source="" title="복도2"/>
    <hotspots height="20" width="180" wordwrap="1" smoothmovement="0">
      <label background="1" borderradius="1" width="180" borderalpha="1" border="1" textcolor="0x000000" backgroundalpha="1" enabled="1" height="20" backgroundcolor="0xffffff" wordwrap="1" bordercolor="0x000000" textalpha="1"/>
      <polystyle backgroundcolor="0x0000ff" borderalpha="1" mode="0" bordercolor="0x0000ff" backgroundalpha="0.25098" handcursor="1"/>
      <hotspot target="" skinid="ht_node" tilt="-20.08" pan="-184.07" id="Point01" url="{node11}" description="" title="거실"/>
      <hotspot target="" skinid="ht_node" tilt="-17.84" pan="-248.08" id="Point02" url="{node14}" description="" title="복도1"/>
      <hotspot target="" skinid="ht_node" tilt="-19.28" pan="-271.92" id="Point03" url="{node12}" description="" title="팬트리"/>
      <hotspot target="" skinid="ht_node" tilt="-36.2" pan="-37.42" id="Point04" url="{node9}" description="" title="주방"/>
    </hotspots>
    <media/>
    <transition zoomin="0" delay="none" type="crossdissolve" zoomspeed="2" zoomafteroutfov="40" enabled="1" softedge="0" zoomfov="40" zoomafterinfov="140" blendcolor="0x000000" zoomout="0" blendtime="1" zoomoutpause="1"/>
    <autorotate nodefilter="" returntohorizon="0.000" noderandom="1" delay="10.00" nodedelay="0.00" horizonfromdefview="0" enabled="1" speed="0.020" useanimation="0" startloaded="0"/>
    <animation syncanimationwithvideo="0" useinautorotation="0" animsequence="Animation01" clipsrandom="0"/>
    <control lockedkeyboardzoom="0" invertcontrol="1" rubberband="0" contextprojections="0" lockedmouse="0" dblclickfullscreen="0" lockedwheel="0" speedwheel="1" lockedkeyboard="0" invertwheel="0" sensitivity="8" contextfullscreen="1" simulatemass="1" hideabout="1" zoomcentercursor="1" contextvr="1"/>
  </panorama>
  <panorama id="node12" hideabout="1">
    <input width="2000" levelbiashidpi="1.000" levelbias="0.400" leveltileurl="tiles/node12/cf_%c/l_%l/c_%x/tile_%y.jpg" overlap="1" height="2000" levelingroll="0" leveltilesize="510" levelingpitch="0">
      <level height="2000" width="2000" preload="0" predecode="0"/>
      <level height="1000" width="1000" preload="0" predecode="0"/>
      <level height="500" width="500" preload="1" predecode="1"/>
      <preview color="0x808080" strip="1"/>
    </input>
    <view pannorth="0" fovmode="2">
      <start tilt="-18.5245" pan="53.2965" fov="149.25" projection="4"/>
      <flyin tilt="-90" pan="0" fov="170" projection="9"/>
      <min tilt="-90" pan="0" fovpixel="2"/>
      <max fovstereographic="330" tilt="90" scaletofit="1" pan="360" fov="140" fovfisheye="360"/>
    </view>
    <userdata tags="202411155052701" longitude="129.140719" customnodeid="" comment="" copyright="" author="" datetime="2024:11:20 09:18:09" altitude="107.32" latitude="35.806231" info="" heading="0" description="" nodeid="node12" source="" title="팬트리"/>
    <hotspots height="20" width="180" wordwrap="1" smoothmovement="0">
      <label background="1" borderradius="1" width="180" borderalpha="1" border="1" textcolor="0x000000" backgroundalpha="1" enabled="1" height="20" backgroundcolor="0xffffff" wordwrap="1" bordercolor="0x000000" textalpha="1"/>
      <polystyle backgroundcolor="0x0000ff" borderalpha="1" mode="0" bordercolor="0x0000ff" backgroundalpha="0.25098" handcursor="1"/>
      <hotspot target="" skinid="ht_node" tilt="-42.99" pan="-177.66" id="Point01" url="{node10}" description="" title="복도2"/>
    </hotspots>
    <media/>
    <transition zoomin="0" delay="none" type="crossdissolve" zoomspeed="2" zoomafteroutfov="40" enabled="1" softedge="0" zoomfov="40" zoomafterinfov="140" blendcolor="0x000000" zoomout="0" blendtime="1" zoomoutpause="1"/>
    <autorotate nodefilter="" returntohorizon="0.000" noderandom="1" delay="10.00" nodedelay="0.00" horizonfromdefview="0" enabled="1" speed="0.020" useanimation="0" startloaded="0"/>
    <animation syncanimationwithvideo="0" useinautorotation="0" animsequence="Animation01" clipsrandom="0"/>
    <control lockedkeyboardzoom="0" invertcontrol="1" rubberband="0" contextprojections="0" lockedmouse="0" dblclickfullscreen="0" lockedwheel="0" speedwheel="1" lockedkeyboard="0" invertwheel="0" sensitivity="8" contextfullscreen="1" simulatemass="1" hideabout="1" zoomcentercursor="1" contextvr="1"/>
  </panorama>
  <panorama id="node11" hideabout="1">
    <input width="2000" levelbiashidpi="1.000" levelbias="0.400" leveltileurl="tiles/node11/cf_%c/l_%l/c_%x/tile_%y.jpg" overlap="1" height="2000" levelingroll="0" leveltilesize="510" levelingpitch="0">
      <level height="2000" width="2000" preload="0" predecode="0"/>
      <level height="1000" width="1000" preload="0" predecode="0"/>
      <level height="500" width="500" preload="1" predecode="1"/>
      <preview color="0x808080" strip="1"/>
    </input>
    <view pannorth="0" fovmode="2">
      <start tilt="-13.8827" pan="109.463" fov="149.25" projection="4"/>
      <flyin tilt="-90" pan="0" fov="170" projection="9"/>
      <min tilt="-90" pan="0" fovpixel="2"/>
      <max fovstereographic="330" tilt="90" scaletofit="1" pan="360" fov="140" fovfisheye="360"/>
    </view>
    <userdata tags="202411155052701" longitude="129.140719" customnodeid="" comment="" copyright="" author="" datetime="2024:11:20 09:18:04" altitude="107.32" latitude="35.806231" info="" heading="0" description="" nodeid="node11" source="" title="거실"/>
    <hotspots height="20" width="180" wordwrap="1" smoothmovement="0">
      <label background="1" borderradius="1" width="180" borderalpha="1" border="1" textcolor="0x000000" backgroundalpha="1" enabled="1" height="20" backgroundcolor="0xffffff" wordwrap="1" bordercolor="0x000000" textalpha="1"/>
      <polystyle backgroundcolor="0x0000ff" borderalpha="1" mode="0" bordercolor="0x0000ff" backgroundalpha="0.25098" handcursor="1"/>
      <hotspot target="" skinid="ht_node" tilt="-18.84" pan="-172.51" id="Point01" url="{node10}" description="" title="복도2"/>
      <hotspot target="" skinid="ht_node" tilt="-11.02" pan="-151.83" id="Point02" url="{node13}" description="" title="침실4"/>
      <hotspot target="" skinid="ht_node" tilt="-17.4" pan="-131.97" id="Point03" url="{node14}" description="" title="복도1"/>
      <hotspot target="" skinid="ht_node" tilt="-16.74" pan="-215.73" id="Point04" url="{node20}" description="" title="침실1"/>
    </hotspots>
    <media/>
    <transition zoomin="0" delay="none" type="crossdissolve" zoomspeed="2" zoomafteroutfov="40" enabled="1" softedge="0" zoomfov="40" zoomafterinfov="140" blendcolor="0x000000" zoomout="0" blendtime="1" zoomoutpause="1"/>
    <autorotate nodefilter="" returntohorizon="0.000" noderandom="1" delay="10.00" nodedelay="0.00" horizonfromdefview="0" enabled="1" speed="0.020" useanimation="0" startloaded="0"/>
    <animation syncanimationwithvideo="0" useinautorotation="0" animsequence="Animation01" clipsrandom="0"/>
    <control lockedkeyboardzoom="0" invertcontrol="1" rubberband="0" contextprojections="0" lockedmouse="0" dblclickfullscreen="0" lockedwheel="0" speedwheel="1" lockedkeyboard="0" invertwheel="0" sensitivity="8" contextfullscreen="1" simulatemass="1" hideabout="1" zoomcentercursor="1" contextvr="1"/>
  </panorama>
  <panorama id="node13" hideabout="1">
    <input width="2000" levelbiashidpi="1.000" levelbias="0.400" leveltileurl="tiles/node13/cf_%c/l_%l/c_%x/tile_%y.jpg" overlap="1" height="2000" levelingroll="0" leveltilesize="510" levelingpitch="0">
      <level height="2000" width="2000" preload="0" predecode="0"/>
      <level height="1000" width="1000" preload="0" predecode="0"/>
      <level height="500" width="500" preload="1" predecode="1"/>
      <preview color="0x808080" strip="1"/>
    </input>
    <view pannorth="0" fovmode="2">
      <start tilt="-19.3876" pan="176.683" fov="149.25" projection="4"/>
      <flyin tilt="-90" pan="0" fov="170" projection="9"/>
      <min tilt="-90" pan="0" fovpixel="2"/>
      <max fovstereographic="330" tilt="90" scaletofit="1" pan="360" fov="140" fovfisheye="360"/>
    </view>
    <userdata tags="202411155052701" longitude="129.140719" customnodeid="" comment="" copyright="" author="" datetime="2024:11:20 09:18:13" altitude="107.32" latitude="35.806231" info="" heading="0" description="" nodeid="node13" source="" title="침실4"/>
    <hotspots height="20" width="180" wordwrap="1" smoothmovement="0">
      <label background="1" borderradius="1" width="180" borderalpha="1" border="1" textcolor="0x000000" backgroundalpha="1" enabled="1" height="20" backgroundcolor="0xffffff" wordwrap="1" bordercolor="0x000000" textalpha="1"/>
      <polystyle backgroundcolor="0x0000ff" borderalpha="1" mode="0" bordercolor="0x0000ff" backgroundalpha="0.25098" handcursor="1"/>
      <hotspot target="" skinid="ht_node" tilt="-23.69" pan="-161.86" id="Point01" url="{node11}" description="" title="거실"/>
    </hotspots>
    <media/>
    <transition zoomin="0" delay="none" type="crossdissolve" zoomspeed="2" zoomafteroutfov="40" enabled="1" softedge="0" zoomfov="40" zoomafterinfov="140" blendcolor="0x000000" zoomout="0" blendtime="1" zoomoutpause="1"/>
    <autorotate nodefilter="" returntohorizon="0.000" noderandom="1" delay="10.00" nodedelay="0.00" horizonfromdefview="0" enabled="1" speed="0.020" useanimation="0" startloaded="0"/>
    <animation syncanimationwithvideo="0" useinautorotation="0" animsequence="Animation01" clipsrandom="0"/>
    <control lockedkeyboardzoom="0" invertcontrol="1" rubberband="0" contextprojections="0" lockedmouse="0" dblclickfullscreen="0" lockedwheel="0" speedwheel="1" lockedkeyboard="0" invertwheel="0" sensitivity="8" contextfullscreen="1" simulatemass="1" hideabout="1" zoomcentercursor="1" contextvr="1"/>
  </panorama>
  <panorama id="node9" hideabout="1">
    <input width="2000" levelbiashidpi="1.000" levelbias="0.400" leveltileurl="tiles/node9/cf_%c/l_%l/c_%x/tile_%y.jpg" overlap="1" height="2000" levelingroll="0" leveltilesize="510" levelingpitch="0">
      <level height="2000" width="2000" preload="0" predecode="0"/>
      <level height="1000" width="1000" preload="0" predecode="0"/>
      <level height="500" width="500" preload="1" predecode="1"/>
      <preview color="0x808080" strip="1"/>
    </input>
    <view pannorth="0" fovmode="2">
      <start tilt="-8.4252" pan="111.985" fov="149.25" projection="4"/>
      <flyin tilt="-90" pan="0" fov="170" projection="9"/>
      <min tilt="-90" pan="0" fovpixel="2"/>
      <max fovstereographic="330" tilt="90" scaletofit="1" pan="360" fov="140" fovfisheye="360"/>
    </view>
    <userdata tags="202411155052701" longitude="129.140719" customnodeid="" comment="" copyright="" author="" datetime="2024:11:20 09:17:55" altitude="107.32" latitude="35.806231" info="" heading="0" description="" nodeid="node9" source="" title="주방"/>
    <hotspots height="20" width="180" wordwrap="1" smoothmovement="0">
      <label background="1" borderradius="1" width="180" borderalpha="1" border="1" textcolor="0x000000" backgroundalpha="1" enabled="1" height="20" backgroundcolor="0xffffff" wordwrap="1" bordercolor="0x000000" textalpha="1"/>
      <polystyle backgroundcolor="0x0000ff" borderalpha="1" mode="0" bordercolor="0x0000ff" backgroundalpha="0.25098" handcursor="1"/>
      <hotspot target="" skinid="ht_node" tilt="-35.63" pan="-159.6" id="Point01" url="{node10}" description="" title="복도2"/>
      <hotspot target="" skinid="ht_node" tilt="-20.2" pan="-91.5" id="Point02" url="{node8}" description="" title="발코니2"/>
    </hotspots>
    <media/>
    <transition zoomin="0" delay="none" type="crossdissolve" zoomspeed="2" zoomafteroutfov="40" enabled="1" softedge="0" zoomfov="40" zoomafterinfov="140" blendcolor="0x000000" zoomout="0" blendtime="1" zoomoutpause="1"/>
    <autorotate nodefilter="" returntohorizon="0.000" noderandom="1" delay="10.00" nodedelay="0.00" horizonfromdefview="0" enabled="1" speed="0.020" useanimation="0" startloaded="0"/>
    <animation syncanimationwithvideo="0" useinautorotation="0" animsequence="Animation01" clipsrandom="0"/>
    <control lockedkeyboardzoom="0" invertcontrol="1" rubberband="0" contextprojections="0" lockedmouse="0" dblclickfullscreen="0" lockedwheel="0" speedwheel="1" lockedkeyboard="0" invertwheel="0" sensitivity="8" contextfullscreen="1" simulatemass="1" hideabout="1" zoomcentercursor="1" contextvr="1"/>
  </panorama>
  <panorama id="node8" hideabout="1">
    <input width="2000" levelbiashidpi="1.000" levelbias="0.400" leveltileurl="tiles/node8/cf_%c/l_%l/c_%x/tile_%y.jpg" overlap="1" height="2000" levelingroll="0" leveltilesize="510" levelingpitch="0">
      <level height="2000" width="2000" preload="0" predecode="0"/>
      <level height="1000" width="1000" preload="0" predecode="0"/>
      <level height="500" width="500" preload="1" predecode="1"/>
      <preview color="0x808080" strip="1"/>
    </input>
    <view pannorth="0" fovmode="2">
      <start tilt="-13.1024" pan="-43.9579" fov="149.25" projection="4"/>
      <flyin tilt="-90" pan="0" fov="170" projection="9"/>
      <min tilt="-90" pan="0" fovpixel="2"/>
      <max fovstereographic="330" tilt="90" scaletofit="1" pan="360" fov="140" fovfisheye="360"/>
    </view>
    <userdata tags="202411155052701" longitude="129.140719" customnodeid="" comment="" copyright="" author="" datetime="2024:11:20 09:17:49" altitude="107.32" latitude="35.806231" info="" heading="0" description="" nodeid="node8" source="" title="발코니2"/>
    <hotspots height="20" width="180" wordwrap="1" smoothmovement="0">
      <label background="1" borderradius="1" width="180" borderalpha="1" border="1" textcolor="0x000000" backgroundalpha="1" enabled="1" height="20" backgroundcolor="0xffffff" wordwrap="1" bordercolor="0x000000" textalpha="1"/>
      <polystyle backgroundcolor="0x0000ff" borderalpha="1" mode="0" bordercolor="0x0000ff" backgroundalpha="0.25098" handcursor="1"/>
      <hotspot target="" skinid="ht_node" tilt="-22.95" pan="-55.91" id="Point01" url="{node7}" description="" title="실외기실"/>
      <hotspot target="" skinid="ht_node" tilt="-31.06" pan="-265.06" id="Point02" url="{node9}" description="" title="주방"/>
    </hotspots>
    <media/>
    <transition zoomin="0" delay="none" type="crossdissolve" zoomspeed="2" zoomafteroutfov="40" enabled="1" softedge="0" zoomfov="40" zoomafterinfov="140" blendcolor="0x000000" zoomout="0" blendtime="1" zoomoutpause="1"/>
    <autorotate nodefilter="" returntohorizon="0.000" noderandom="1" delay="10.00" nodedelay="0.00" horizonfromdefview="0" enabled="1" speed="0.020" useanimation="0" startloaded="0"/>
    <animation syncanimationwithvideo="0" useinautorotation="0" animsequence="Animation01" clipsrandom="0"/>
    <control lockedkeyboardzoom="0" invertcontrol="1" rubberband="0" contextprojections="0" lockedmouse="0" dblclickfullscreen="0" lockedwheel="0" speedwheel="1" lockedkeyboard="0" invertwheel="0" sensitivity="8" contextfullscreen="1" simulatemass="1" hideabout="1" zoomcentercursor="1" contextvr="1"/>
  </panorama>
  <panorama id="node7" hideabout="1">
    <input width="2000" levelbiashidpi="1.000" levelbias="0.400" leveltileurl="tiles/node7/cf_%c/l_%l/c_%x/tile_%y.jpg" overlap="1" height="2000" levelingroll="0" leveltilesize="510" levelingpitch="0">
      <level height="2000" width="2000" preload="0" predecode="0"/>
      <level height="1000" width="1000" preload="0" predecode="0"/>
      <level height="500" width="500" preload="1" predecode="1"/>
      <preview color="0x808080" strip="1"/>
    </input>
    <view pannorth="0" fovmode="2">
      <start tilt="-35.2433" pan="37.2134" fov="137.973" projection="4"/>
      <flyin tilt="-90" pan="0" fov="170" projection="9"/>
      <min tilt="-90" pan="0" fovpixel="2"/>
      <max fovstereographic="330" tilt="90" scaletofit="1" pan="360" fov="140" fovfisheye="360"/>
    </view>
    <userdata tags="202411155052701" longitude="129.140719" customnodeid="" comment="" copyright="" author="" datetime="2024:11:20 09:17:45" altitude="107.32" latitude="35.806231" info="" heading="0" description="" nodeid="node7" source="" title="실외기실"/>
    <hotspots height="20" width="180" wordwrap="1" smoothmovement="0">
      <label background="1" borderradius="1" width="180" borderalpha="1" border="1" textcolor="0x000000" backgroundalpha="1" enabled="1" height="20" backgroundcolor="0xffffff" wordwrap="1" bordercolor="0x000000" textalpha="1"/>
      <polystyle backgroundcolor="0x0000ff" borderalpha="1" mode="0" bordercolor="0x0000ff" backgroundalpha="0.25098" handcursor="1"/>
      <hotspot target="" skinid="ht_node" tilt="-44.04" pan="-231.87" id="Point01" url="{node8}" description="" title="발코니2"/>
    </hotspots>
    <media/>
    <transition zoomin="0" delay="none" type="crossdissolve" zoomspeed="2" zoomafteroutfov="40" enabled="1" softedge="0" zoomfov="40" zoomafterinfov="140" blendcolor="0x000000" zoomout="0" blendtime="1" zoomoutpause="1"/>
    <autorotate nodefilter="" returntohorizon="0.000" noderandom="1" delay="10.00" nodedelay="0.00" horizonfromdefview="0" enabled="1" speed="0.020" useanimation="0" startloaded="0"/>
    <animation syncanimationwithvideo="0" useinautorotation="0" animsequence="Animation01" clipsrandom="0"/>
    <control lockedkeyboardzoom="0" invertcontrol="1" rubberband="0" contextprojections="0" lockedmouse="0" dblclickfullscreen="0" lockedwheel="0" speedwheel="1" lockedkeyboard="0" invertwheel="0" sensitivity="8" contextfullscreen="1" simulatemass="1" hideabout="1" zoomcentercursor="1" contextvr="1"/>
  </panorama>
  <panorama id="node20" hideabout="1">
    <input width="2000" levelbiashidpi="1.000" levelbias="0.400" leveltileurl="tiles/node20/cf_%c/l_%l/c_%x/tile_%y.jpg" overlap="1" height="2000" levelingroll="0" leveltilesize="510" levelingpitch="0">
      <level height="2000" width="2000" preload="0" predecode="0"/>
      <level height="1000" width="1000" preload="0" predecode="0"/>
      <level height="500" width="500" preload="1" predecode="1"/>
      <preview color="0x808080" strip="1"/>
    </input>
    <view pannorth="0" fovmode="2">
      <start tilt="-12.9868" pan="-5.26951" fov="149.25" projection="4"/>
      <flyin tilt="-90" pan="0" fov="170" projection="9"/>
      <min tilt="-90" pan="0" fovpixel="2"/>
      <max fovstereographic="330" tilt="90" scaletofit="1" pan="360" fov="140" fovfisheye="360"/>
    </view>
    <userdata tags="202411155052701" longitude="129.140719" customnodeid="" comment="" copyright="" author="" datetime="2024:11:20 09:18:47" altitude="107.32" latitude="35.806231" info="" heading="0" description="" nodeid="node20" source="" title="침실1"/>
    <hotspots height="20" width="180" wordwrap="1" smoothmovement="0">
      <label background="1" borderradius="1" width="180" borderalpha="1" border="1" textcolor="0x000000" backgroundalpha="1" enabled="1" height="20" backgroundcolor="0xffffff" wordwrap="1" bordercolor="0x000000" textalpha="1"/>
      <polystyle backgroundcolor="0x0000ff" borderalpha="1" mode="0" bordercolor="0x0000ff" backgroundalpha="0.25098" handcursor="1"/>
      <hotspot target="" skinid="ht_node" tilt="-30.19" pan="-35.32" id="Point01" url="{node19}" description="" title="발코니1"/>
      <hotspot target="" skinid="ht_node" tilt="-26.56" pan="-141.89" id="Point02" url="{node11}" description="" title="거실"/>
      <hotspot target="" skinid="ht_node" tilt="-24.71" pan="-207.04" id="Point03" url="{node17}" description="" title="파우더룸"/>
    </hotspots>
    <media/>
    <transition zoomin="0" delay="none" type="crossdissolve" zoomspeed="2" zoomafteroutfov="40" enabled="1" softedge="0" zoomfov="40" zoomafterinfov="140" blendcolor="0x000000" zoomout="0" blendtime="1" zoomoutpause="1"/>
    <autorotate nodefilter="" returntohorizon="0.000" noderandom="1" delay="10.00" nodedelay="0.00" horizonfromdefview="0" enabled="1" speed="0.020" useanimation="0" startloaded="0"/>
    <animation syncanimationwithvideo="0" useinautorotation="0" animsequence="Animation01" clipsrandom="0"/>
    <control lockedkeyboardzoom="0" invertcontrol="1" rubberband="0" contextprojections="0" lockedmouse="0" dblclickfullscreen="0" lockedwheel="0" speedwheel="1" lockedkeyboard="0" invertwheel="0" sensitivity="8" contextfullscreen="1" simulatemass="1" hideabout="1" zoomcentercursor="1" contextvr="1"/>
  </panorama>
  <panorama id="node17" hideabout="1">
    <input width="2000" levelbiashidpi="1.000" levelbias="0.400" leveltileurl="tiles/node17/cf_%c/l_%l/c_%x/tile_%y.jpg" overlap="1" height="2000" levelingroll="0" leveltilesize="510" levelingpitch="0">
      <level height="2000" width="2000" preload="0" predecode="0"/>
      <level height="1000" width="1000" preload="0" predecode="0"/>
      <level height="500" width="500" preload="1" predecode="1"/>
      <preview color="0x808080" strip="1"/>
    </input>
    <view pannorth="0" fovmode="2">
      <start tilt="-10.4957" pan="-37.3627" fov="149.25" projection="4"/>
      <flyin tilt="-90" pan="0" fov="170" projection="9"/>
      <min tilt="-90" pan="0" fovpixel="2"/>
      <max fovstereographic="330" tilt="90" scaletofit="1" pan="360" fov="140" fovfisheye="360"/>
    </view>
    <userdata tags="202411155052701" longitude="129.140719" customnodeid="" comment="" copyright="" author="" datetime="2024:11:20 09:18:33" altitude="107.32" latitude="35.806231" info="" heading="0" description="" nodeid="node17" source="" title="파우더룸"/>
    <hotspots height="20" width="180" wordwrap="1" smoothmovement="0">
      <label background="1" borderradius="1" width="180" borderalpha="1" border="1" textcolor="0x000000" backgroundalpha="1" enabled="1" height="20" backgroundcolor="0xffffff" wordwrap="1" bordercolor="0x000000" textalpha="1"/>
      <polystyle backgroundcolor="0x0000ff" borderalpha="1" mode="0" bordercolor="0x0000ff" backgroundalpha="0.25098" handcursor="1"/>
      <hotspot target="" skinid="ht_node" tilt="-46.82" pan="-178.01" id="Point01" url="{node16}" description="" title="욕실2"/>
      <hotspot target="" skinid="ht_node" tilt="-17.97" pan="-267.02" id="Point02" url="{node15}" description="" title="드레스룸"/>
      <hotspot target="" skinid="ht_node" tilt="-38.26" pan="-92.68" id="Point03" url="{node20}" description="" title="침실1"/>
    </hotspots>
    <media/>
    <transition zoomin="0" delay="none" type="crossdissolve" zoomspeed="2" zoomafteroutfov="40" enabled="1" softedge="0" zoomfov="40" zoomafterinfov="140" blendcolor="0x000000" zoomout="0" blendtime="1" zoomoutpause="1"/>
    <autorotate nodefilter="" returntohorizon="0.000" noderandom="1" delay="10.00" nodedelay="0.00" horizonfromdefview="0" enabled="1" speed="0.020" useanimation="0" startloaded="0"/>
    <animation syncanimationwithvideo="0" useinautorotation="0" animsequence="Animation01" clipsrandom="0"/>
    <control lockedkeyboardzoom="0" invertcontrol="1" rubberband="0" contextprojections="0" lockedmouse="0" dblclickfullscreen="0" lockedwheel="0" speedwheel="1" lockedkeyboard="0" invertwheel="0" sensitivity="8" contextfullscreen="1" simulatemass="1" hideabout="1" zoomcentercursor="1" contextvr="1"/>
  </panorama>
  <panorama id="node15" hideabout="1">
    <input width="2000" levelbiashidpi="1.000" levelbias="0.400" leveltileurl="tiles/node15/cf_%c/l_%l/c_%x/tile_%y.jpg" overlap="1" height="2000" levelingroll="0" leveltilesize="510" levelingpitch="0">
      <level height="2000" width="2000" preload="0" predecode="0"/>
      <level height="1000" width="1000" preload="0" predecode="0"/>
      <level height="500" width="500" preload="1" predecode="1"/>
      <preview color="0x808080" strip="1"/>
    </input>
    <view pannorth="0" fovmode="2">
      <start tilt="-16.0661" pan="-179.492" fov="149.25" projection="4"/>
      <flyin tilt="-90" pan="0" fov="170" projection="9"/>
      <min tilt="-90" pan="0" fovpixel="2"/>
      <max fovstereographic="330" tilt="90" scaletofit="1" pan="360" fov="140" fovfisheye="360"/>
    </view>
    <userdata tags="202411155052701" longitude="129.140719" customnodeid="" comment="" copyright="" author="" datetime="2024:11:20 09:18:23" altitude="107.32" latitude="35.806231" info="" heading="0" description="" nodeid="node15" source="" title="드레스룸"/>
    <hotspots height="20" width="180" wordwrap="1" smoothmovement="0">
      <label background="1" borderradius="1" width="180" borderalpha="1" border="1" textcolor="0x000000" backgroundalpha="1" enabled="1" height="20" backgroundcolor="0xffffff" wordwrap="1" bordercolor="0x000000" textalpha="1"/>
      <polystyle backgroundcolor="0x0000ff" borderalpha="1" mode="0" bordercolor="0x0000ff" backgroundalpha="0.25098" handcursor="1"/>
      <hotspot target="" skinid="ht_node" tilt="-31.5" pan="-184.12" id="Point01" url="{node17}" description="" title="파우더룸"/>
    </hotspots>
    <media/>
    <transition zoomin="0" delay="none" type="crossdissolve" zoomspeed="2" zoomafteroutfov="40" enabled="1" softedge="0" zoomfov="40" zoomafterinfov="140" blendcolor="0x000000" zoomout="0" blendtime="1" zoomoutpause="1"/>
    <autorotate nodefilter="" returntohorizon="0.000" noderandom="1" delay="10.00" nodedelay="0.00" horizonfromdefview="0" enabled="1" speed="0.020" useanimation="0" startloaded="0"/>
    <animation syncanimationwithvideo="0" useinautorotation="0" animsequence="Animation01" clipsrandom="0"/>
    <control lockedkeyboardzoom="0" invertcontrol="1" rubberband="0" contextprojections="0" lockedmouse="0" dblclickfullscreen="0" lockedwheel="0" speedwheel="1" lockedkeyboard="0" invertwheel="0" sensitivity="8" contextfullscreen="1" simulatemass="1" hideabout="1" zoomcentercursor="1" contextvr="1"/>
  </panorama>
  <panorama id="node16" hideabout="1">
    <input width="2000" levelbiashidpi="1.000" levelbias="0.400" leveltileurl="tiles/node16/cf_%c/l_%l/c_%x/tile_%y.jpg" overlap="1" height="2000" levelingroll="0" leveltilesize="510" levelingpitch="0">
      <level height="2000" width="2000" preload="0" predecode="0"/>
      <level height="1000" width="1000" preload="0" predecode="0"/>
      <level height="500" width="500" preload="1" predecode="1"/>
      <preview color="0x808080" strip="1"/>
    </input>
    <view pannorth="0" fovmode="2">
      <start tilt="-17.1504" pan="43.5178" fov="149.25" projection="4"/>
      <flyin tilt="-90" pan="0" fov="170" projection="9"/>
      <min tilt="-90" pan="0" fovpixel="2"/>
      <max fovstereographic="330" tilt="90" scaletofit="1" pan="360" fov="140" fovfisheye="360"/>
    </view>
    <userdata tags="202411155052701" longitude="129.140719" customnodeid="" comment="" copyright="" author="" datetime="2024:11:20 09:18:28" altitude="107.32" latitude="35.806231" info="" heading="0" description="" nodeid="node16" source="" title="욕실2"/>
    <hotspots height="20" width="180" wordwrap="1" smoothmovement="0">
      <label background="1" borderradius="1" width="180" borderalpha="1" border="1" textcolor="0x000000" backgroundalpha="1" enabled="1" height="20" backgroundcolor="0xffffff" wordwrap="1" bordercolor="0x000000" textalpha="1"/>
      <polystyle backgroundcolor="0x0000ff" borderalpha="1" mode="0" bordercolor="0x0000ff" backgroundalpha="0.25098" handcursor="1"/>
      <hotspot target="" skinid="ht_node" tilt="-37.02" pan="-110.79" id="Point01" url="{node17}" description="" title="파우더룸"/>
    </hotspots>
    <media/>
    <transition zoomin="0" delay="none" type="crossdissolve" zoomspeed="2" zoomafteroutfov="40" enabled="1" softedge="0" zoomfov="40" zoomafterinfov="140" blendcolor="0x000000" zoomout="0" blendtime="1" zoomoutpause="1"/>
    <autorotate nodefilter="" returntohorizon="0.000" noderandom="1" delay="10.00" nodedelay="0.00" horizonfromdefview="0" enabled="1" speed="0.020" useanimation="0" startloaded="0"/>
    <animation syncanimationwithvideo="0" useinautorotation="0" animsequence="Animation01" clipsrandom="0"/>
    <control lockedkeyboardzoom="0" invertcontrol="1" rubberband="0" contextprojections="0" lockedmouse="0" dblclickfullscreen="0" lockedwheel="0" speedwheel="1" lockedkeyboard="0" invertwheel="0" sensitivity="8" contextfullscreen="1" simulatemass="1" hideabout="1" zoomcentercursor="1" contextvr="1"/>
  </panorama>
  <panorama id="node19" hideabout="1">
    <input width="2000" levelbiashidpi="1.000" levelbias="0.400" leveltileurl="tiles/node19/cf_%c/l_%l/c_%x/tile_%y.jpg" overlap="1" height="2000" levelingroll="0" leveltilesize="510" levelingpitch="0">
      <level height="2000" width="2000" preload="0" predecode="0"/>
      <level height="1000" width="1000" preload="0" predecode="0"/>
      <level height="500" width="500" preload="1" predecode="1"/>
      <preview color="0x808080" strip="1"/>
    </input>
    <view pannorth="0" fovmode="2">
      <start tilt="-14.9779" pan="-34.963" fov="137.973" projection="4"/>
      <flyin tilt="-90" pan="0" fov="170" projection="9"/>
      <min tilt="-90" pan="0" fovpixel="2"/>
      <max fovstereographic="330" tilt="90" scaletofit="1" pan="360" fov="140" fovfisheye="360"/>
    </view>
    <userdata tags="202411155052701" longitude="129.140719" customnodeid="" comment="" copyright="" author="" datetime="2024:11:20 09:18:42" altitude="107.32" latitude="35.806231" info="" heading="0" description="" nodeid="node19" source="" title="발코니1"/>
    <hotspots height="20" width="180" wordwrap="1" smoothmovement="0">
      <label background="1" borderradius="1" width="180" borderalpha="1" border="1" textcolor="0x000000" backgroundalpha="1" enabled="1" height="20" backgroundcolor="0xffffff" wordwrap="1" bordercolor="0x000000" textalpha="1"/>
      <polystyle backgroundcolor="0x0000ff" borderalpha="1" mode="0" bordercolor="0x0000ff" backgroundalpha="0.25098" handcursor="1"/>
      <hotspot target="" skinid="ht_node" tilt="-40.94" pan="-149.68" id="Point01" url="{node20}" description="" title="침실1"/>
      <hotspot target="" skinid="ht_node" tilt="-16.54" pan="-259.97" id="Point02" url="{node18}" description="" title="대피공간"/>
    </hotspots>
    <media/>
    <transition zoomin="0" delay="none" type="crossdissolve" zoomspeed="2" zoomafteroutfov="40" enabled="1" softedge="0" zoomfov="40" zoomafterinfov="140" blendcolor="0x000000" zoomout="0" blendtime="1" zoomoutpause="1"/>
    <autorotate nodefilter="" returntohorizon="0.000" noderandom="1" delay="10.00" nodedelay="0.00" horizonfromdefview="0" enabled="1" speed="0.020" useanimation="0" startloaded="0"/>
    <animation syncanimationwithvideo="0" useinautorotation="0" animsequence="Animation01" clipsrandom="0"/>
    <control lockedkeyboardzoom="0" invertcontrol="1" rubberband="0" contextprojections="0" lockedmouse="0" dblclickfullscreen="0" lockedwheel="0" speedwheel="1" lockedkeyboard="0" invertwheel="0" sensitivity="8" contextfullscreen="1" simulatemass="1" hideabout="1" zoomcentercursor="1" contextvr="1"/>
  </panorama>
  <panorama id="node18" hideabout="1">
    <input width="2000" levelbiashidpi="1.000" levelbias="0.400" leveltileurl="tiles/node18/cf_%c/l_%l/c_%x/tile_%y.jpg" overlap="1" height="2000" levelingroll="0" leveltilesize="510" levelingpitch="0">
      <level height="2000" width="2000" preload="0" predecode="0"/>
      <level height="1000" width="1000" preload="0" predecode="0"/>
      <level height="500" width="500" preload="1" predecode="1"/>
      <preview color="0x808080" strip="1"/>
    </input>
    <view pannorth="0" fovmode="2">
      <start tilt="-17.0248" pan="-79.0287" fov="149.25" projection="4"/>
      <flyin tilt="-90" pan="0" fov="170" projection="9"/>
      <min tilt="-90" pan="0" fovpixel="2"/>
      <max fovstereographic="330" tilt="90" scaletofit="1" pan="360" fov="140" fovfisheye="360"/>
    </view>
    <userdata tags="202411155052701" longitude="129.140719" customnodeid="" comment="" copyright="" author="" datetime="2024:11:20 09:18:37" altitude="107.32" latitude="35.806231" info="" heading="0" description="" nodeid="node18" source="" title="대피공간"/>
    <hotspots height="20" width="180" wordwrap="1" smoothmovement="0">
      <label background="1" borderradius="1" width="180" borderalpha="1" border="1" textcolor="0x000000" backgroundalpha="1" enabled="1" height="20" backgroundcolor="0xffffff" wordwrap="1" bordercolor="0x000000" textalpha="1"/>
      <polystyle backgroundcolor="0x0000ff" borderalpha="1" mode="0" bordercolor="0x0000ff" backgroundalpha="0.25098" handcursor="1"/>
      <hotspot target="" skinid="ht_node" tilt="-22.25" pan="-103.18" id="Point01" url="{node19}" description="" title="발코니1"/>
    </hotspots>
    <media/>
    <transition zoomin="0" delay="none" type="crossdissolve" zoomspeed="2" zoomafteroutfov="40" enabled="1" softedge="0" zoomfov="40" zoomafterinfov="140" blendcolor="0x000000" zoomout="0" blendtime="1" zoomoutpause="1"/>
    <autorotate nodefilter="" returntohorizon="0.000" noderandom="1" delay="10.00" nodedelay="0.00" horizonfromdefview="0" enabled="1" speed="0.020" useanimation="0" startloaded="0"/>
    <animation syncanimationwithvideo="0" useinautorotation="0" animsequence="Animation01" clipsrandom="0"/>
    <control lockedkeyboardzoom="0" invertcontrol="1" rubberband="0" contextprojections="0" lockedmouse="0" dblclickfullscreen="0" lockedwheel="0" speedwheel="1" lockedkeyboard="0" invertwheel="0" sensitivity="8" contextfullscreen="1" simulatemass="1" hideabout="1" zoomcentercursor="1" contextvr="1"/>
  </panorama>
  <masternode>
    <userdata tags="" comment="" copyright="" description="505동 2701호" author="" title="대전 천동 리더스시티"/>
    <animationsequences>
      <sequence title="Animation01"/>
    </animationsequences>
  </masternode>
</tour>
